<metadata xml:lang="en"><Esri><CreaDate>20150114</CreaDate><CreaTime>08343500</CreaTime><ArcGISFormat>1.0</ArcGISFormat><SyncOnce>TRUE</SyncOnce><ModDate>20170522</ModDate><ModTime>21261000</ModTime><scaleRange><minScale>150000000</minScale><maxScale>5000</maxScale></scaleRange><ArcGISProfile>ItemDescription</ArcGISProfile></Esri><dataIdInfo><idCitation><resTitle>Export Data Driven Pages</resTitle></idCitation><idAbs>&lt;DIV STYLE="text-align:Left;"&gt;&lt;DIV&gt;&lt;P&gt;&lt;SPAN&gt;This tool exports all the data driven pages in a map document.&lt;/SPAN&gt;&lt;/P&gt;&lt;/DIV&gt;&lt;/DIV&gt;</idAbs><idCredit>An Tran</idCredit><searchKeys><keyword>Export</keyword><keyword>Maps</keyword><keyword>Data</keyword><keyword>Driven</keyword><keyword>Pages</keyword></searchKeys></dataIdInfo><distInfo><distributor><distorFormat><formatName>ArcToolbox Tool</formatName></distorFormat></distributor></distInfo><tool displayname="Export Data Driven Pages" name="ExportDDP" toolboxalias="CustomPythonTools" xmlns=""><parameters><param datatype="File" direction="Input" displayname="Map File" expression="mapFile" name="mapFile" type="Required"><dialogReference>&lt;DIV STYLE="text-align:Left;"&gt;&lt;DIV&gt;&lt;P&gt;&lt;SPAN&gt;The map document to export from.&lt;/SPAN&gt;&lt;/P&gt;&lt;/DIV&gt;&lt;/DIV&gt;</dialogReference><pythonReference>&lt;DIV STYLE="text-align:Left;"&gt;&lt;DIV&gt;&lt;P&gt;&lt;SPAN&gt;A DEFile specifying the map document to export from.&lt;/SPAN&gt;&lt;/P&gt;&lt;/DIV&gt;&lt;/DIV&gt;</pythonReference></param><param datatype="Folder" direction="Input" displayname="Output Location" expression="outDir" name="outDir" type="Required"><dialogReference>&lt;DIV STYLE="text-align:Left;"&gt;&lt;DIV&gt;&lt;P&gt;&lt;SPAN&gt;The output folder where exported files will be saved.&lt;/SPAN&gt;&lt;/P&gt;&lt;/DIV&gt;&lt;/DIV&gt;</dialogReference><pythonReference>&lt;DIV STYLE="text-align:Left;"&gt;&lt;DIV&gt;&lt;P&gt;&lt;SPAN&gt;A DEFolder specifying where output will be saved.&lt;/SPAN&gt;&lt;/P&gt;&lt;/DIV&gt;&lt;/DIV&gt;</pythonReference></param><param datatype="Multiple Value" direction="Input" displayname="Data Driven Pages List" expression="exportList;exportList..." name="exportList" type="Required"><dialogReference>&lt;DIV STYLE="text-align:Left;"&gt;&lt;DIV&gt;&lt;P&gt;&lt;SPAN&gt;The pages in the data driven document to be exported.&lt;/SPAN&gt;&lt;/P&gt;&lt;/DIV&gt;&lt;/DIV&gt;</dialogReference><pythonReference>&lt;DIV STYLE="text-align:Left;"&gt;&lt;DIV&gt;&lt;P&gt;&lt;SPAN&gt;A GPString specifying which pages of he data driven document to export.&lt;/SPAN&gt;&lt;/P&gt;&lt;/DIV&gt;&lt;/DIV&gt;</pythonReference></param><param datatype="String" direction="Input" displayname="Output Format" expression="JPEG | PDF | PNG" name="outFormat" type="Required"><dialogReference>&lt;DIV STYLE="text-align:Left;"&gt;&lt;DIV&gt;&lt;P&gt;&lt;SPAN&gt;The output file format.&lt;/SPAN&gt;&lt;/P&gt;&lt;/DIV&gt;&lt;/DIV&gt;</dialogReference><pythonReference>&lt;DIV STYLE="text-align:Left;"&gt;&lt;DIV&gt;&lt;P&gt;&lt;SPAN&gt;A GPString specifying the output format. Valid values are PDF, PNG, and JPEG&lt;/SPAN&gt;&lt;/P&gt;&lt;/DIV&gt;&lt;/DIV&gt;</pythonReference></param></parameters><arcToolboxHelpPath>c:\program files (x86)\arcgis\desktop10.4\Help\gp</arcToolboxHelpPath><summary>&lt;DIV STYLE="text-align:Left;"&gt;&lt;DIV&gt;&lt;P&gt;&lt;SPAN&gt;This tool exports all the data driven pages in a map document.&lt;/SPAN&gt;&lt;/P&gt;&lt;/DIV&gt;&lt;/DIV&gt;</summary><usage>&lt;DIV STYLE="text-align:Left;"&gt;&lt;DIV&gt;&lt;P&gt;&lt;SPAN&gt;This tool is meant to supplement the existing data driven pages export function in ArcMap by allowing users to export multiple pages to formats other than PDF. Currently supported outputs include PDF, PNG, and JPEG.&lt;/SPAN&gt;&lt;/P&gt;&lt;/DIV&gt;&lt;/DIV&gt;</usage></tool><mdHrLv><ScopeCd value="005"></ScopeCd></mdHrLv></metadata>
